monitoring_exam/__init__.py
monitoring_exam/app.py
monitoring_exam/integration-test.py
monitoring_exam/unit-test.py
monitoring_exam-0.0.1.dist-info/METADATA
monitoring_exam-0.0.1.dist-info/WHEEL
monitoring_exam-0.0.1.dist-info/top_level.txt
monitoring_exam-0.0.1.dist-info/RECORD
