Metadata-Version: 2.1
Name: monitoring-exam
Version: 0.0.1
Summary: Gestione degli esami universitari
Home-page: UNKNOWN
Author: Nada Mohamed, Alessia Rubini, Marco Piccinini
License: MIT
Platform: UNKNOWN
Classifier: Programming Language :: Python :: 3
Classifier: License :: OSI Approved :: MIT License
Classifier: Operating System :: OS Independent
